PAGEpy/PAGEpy_plot.py
PAGEpy/PAGEpy_utils.py
PAGEpy/__init__.py
PAGEpy/format_data_class.py
PAGEpy/individual_fold_class.py
PAGEpy/multiple_folds_class.py
PAGEpy/pred_ann_model.py
PAGEpy/pso.py
pagepy-1.0.13.dist-info/METADATA
pagepy-1.0.13.dist-info/WHEEL
pagepy-1.0.13.dist-info/licenses/LICENSE
pagepy-1.0.13.dist-info/RECORD
