Metadata-Version: 2.4
Name: PAGEpy
Version: 1.0.13
Summary: Predictive Analysis of Gene Expression
Project-URL: Homepage, https://github.com/sean-otoole/PAGEpy
Author-email: Sean O'Toole <sean.otoole.bio@gmail.com>
License-Expression: MIT
License-File: LICENSE
Classifier: Operating System :: OS Independent
Classifier: Programming Language :: Python :: 3
Requires-Python: >=3.8
Requires-Dist: anndata<0.11,>=0.8.0
Requires-Dist: matplotlib<3.8,>=3.4
Requires-Dist: numpy==1.26.4
Requires-Dist: pandas==2.2.3
Requires-Dist: scanpy<1.10,>=1.9.1
Requires-Dist: scikit-learn<1.5,>=1.0
Requires-Dist: scipy==1.13.1
Requires-Dist: seaborn<0.13,>=0.11.0
Requires-Dist: tensorflow==2.18.0
